Part1/mux8.vhdl
library IEEE;
use IEEE.STD_LOGIC_1164.ALL;

entity mux8 is
    Port (  I0 : in std_logic_vector (7 downto 0);
            I1 : in std_logic_vector (7 downto 0);
            I2 : in std_logic_vector (7 downto 0);
            I3 : in std_logic_vector (7 downto 0);
            S : in std_logic_vector (1 downto 0);
            Y : out std_logic_vector (7 downto 0));
end mux8;

architecture Behavioral of mux8 is

begin
    process(I0,I1,I2,I3,S) is
    begin
        case S is
            when "00" => Y <= I0;
            when "01" => Y <= I1;
            when "10" => Y <= I2;
            when others => Y <= I3;
        end case;
    end process;

end Behavioral;

Part1/reg.vhdl
library ieee;
use ieee.std_logic_1164.all;

entity reg is
port(
  I: in std_logic_vector (7 downto 0); -- for loading
  clock: in std_logic; -- rising-edge triggering 
  enable: in std_logic; -- 0: don't do anything; 1: reg is enabled
  O: out std_logic_vector (7 downto 0) := (others => '0') -- output
);
end reg;

architecture behav of reg is

begin
    process(clock)
    begin
      if rising_edge(clock) then
        -- Write to register when enable = '1'
        if (enable = '1') then
          O <= I;
        end if;
      end if;
    end process;
end behav;

Part1/demux.vhdl
library IEEE;
use IEEE.STD_LOGIC_1164.ALL;

entity demux8 is
    Port ( I : in std_logic;
           S : in std_logic_vector (1 downto 0);
           Y : out std_logic_vector (3 downto 0) := (others=>'0')
           );
end demux8;

architecture Behavioral of demux8 is

begin
    process(I,S) is
    begin
        -- Ensures that only one register is writing
        Y <= "0000";
        case S is
            when "00" => Y(0) <= I;
            when "01" => Y(1) <= I;
            when "10" => Y(2) <= I;
            when others => Y(3) <= I;
        end case;
    end process;
end Behavioral;

Part1/regb.vhdl
library ieee;
use ieee.std_logic_1164.all;

entity regb is
    Port (  wd: in std_logic_vector (7 downto 0) := (others=>'0');
            ws: in std_logic_vector (1 downto 0) := (others=>'0');
            rs1: in std_logic_vector (1 downto 0) := (others=>'0');
            rs2: in std_logic_vector (1 downto 0) := (others=>'0');
            clk, we: in std_logic;
            rd1: out std_logic_vector (7 downto 0) := (others=>'0');
            rd2: out std_logic_vector (7 downto 0) := (others=>'0')
            );
end regb;

architecture behav of regb is
--  Declaration of the component that will be instantiated.


component demux8 is
    port (  I : in std_logic;
            S : in std_logic_vector (1 downto 0);
            Y : out std_logic_vector (3 downto 0) := (others=>'0')
            );
end component;

component reg is
    port(	
        I:	    in std_logic_vector (7 downto 0); -- for loading
        clock:	in std_logic; -- rising-edge triggering 
        enable:	in std_logic; -- 0: don't do anything; 1: reg is enabled
        O:	    out std_logic_vector(7 downto 0) := (others=>'0') -- output the current register content. 
    );
end component;

component mux8 is
    Port (  I0 : in std_logic_vector (7 downto 0);
            I1 : in std_logic_vector (7 downto 0);
            I2 : in std_logic_vector (7 downto 0);
            I3 : in std_logic_vector (7 downto 0);
            S : in std_logic_vector (1 downto 0);
            Y : out std_logic_vector (7 downto 0) := (others=>'0')
            );
end component;
    
-- Write enable wires that connect demux to registers
signal W : std_logic_vector (3 downto 0) := (others=>'0');
-- Read wires that connect registers to mux
signal R0 : std_logic_vector (7 downto 0) := (others=>'0');
signal R1 : std_logic_vector (7 downto 0) := (others=>'0');
signal R2 : std_logic_vector (7 downto 0) := (others=>'0');
signal R3 : std_logic_vector (7 downto 0) := (others=>'0');

begin
--  Component instantiation.
demuxws: demux8 port map ( I => we, S => ws, Y => W);
reg0: reg port map (i => wd, clock => clk, enable => W(0), O => R0);
reg1: reg port map (i => wd, clock => clk, enable => W(1), O => R1);
reg2: reg port map (i => wd, clock => clk, enable => W(2), O => R2);
reg3: reg port map (i => wd, clock => clk, enable => W(3), O => R3);
muxrd1: mux8 port map ( I0 => R0, I1 => R1, I2 => R2, I3 => R3, S => rs1, Y => rd1);
muxrd2: mux8 port map ( I0 => R0, I1 => R1, I2 => R2, I3 => R3, S => rs2, Y => rd2);

end behav;

Part1/regbTB.vhdl
library ieee;
use ieee.std_logic_1164.all;

entity regb_tb is
end regb_tb;

architecture behav of regb_tb is
--  Declaration of the component that will be instantiated.

component regb is
    Port (  wd: in std_logic_vector (7 downto 0) := (others=>'0');
            ws: in std_logic_vector (1 downto 0) := (others=>'0');
            rs1: in std_logic_vector (1 downto 0) := (others=>'0');
            rs2: in std_logic_vector (1 downto 0) := (others=>'0');
            clk, we: in std_logic;
            rd1: out std_logic_vector (7 downto 0) := (others=>'0');
            rd2: out std_logic_vector (7 downto 0) := (others=>'0')
            );
end component;

-- Input and output signal declaration
signal wd : std_logic_vector (7 downto 0) := (others=>'0');
signal ws : std_logic_vector (1 downto 0) := (others=>'0');
signal rs1 : std_logic_vector (1 downto 0) := (others=>'0');
signal rs2 : std_logic_vector (1 downto 0) := (others=>'0');
signal clk, we : std_logic;
signal rd1 : std_logic_vector (7 downto 0) := (others=>'0');
signal rd2 : std_logic_vector (7 downto 0) := (others=>'0');

begin
-- Component Instantiation
regbank : regb port map( wd => wd, ws => ws, rs1 => rs1, rs2 => rs2, clk => clk, we => we, rd1 => rd1, rd2 => rd2);

--  This process does the real job.
process
type pattern_type is record
--  The inputs of the reg.
	wd : std_logic_vector (7 downto 0);
    ws : std_logic_vector (1 downto 0);
	rs1 : std_logic_vector (1 downto 0);
	rs2 : std_logic_vector (1 downto 0);
	clk, we : std_logic;
--  The expected outputs of the reg.
	rd1: std_logic_vector (7 downto 0);
	rd2: std_logic_vector (7 downto 0);
end record;
--  The patterns to apply.
type pattern_array is array (natural range <>) of pattern_type;
constant patterns : pattern_array :=
--    wd    ,  ws ,  rs1,  rs2, clk,  we,     rd1   ,     rd2
(("00000100", "00", "00", "01", '0', '1', "00000000", "00000000"),
("00000100", "00", "00", "01", '1', '1', "00000100", "00000000"),
("00000000", "01", "10", "01", '0', '1', "00000000", "00000000"),
("00100000", "01", "00", "01", '1', '0', "00000100", "00100000"),
("00000100", "00", "00", "01", '0', '0', "00000100", "00100000"),
("00000100", "00", "00", "01", '1', '0', "00000100", "00100000"),
("00000010", "11", "10", "11", '0', '1', "00000000", "00000000"),
("00000100", "11", "10", "11", '1', '1', "00000000", "00000100"),
("00001000", "10", "10", "11", '0', '1', "00000000", "00000100"),
("00001000", "10", "10", "01", '1', '1', "00001000", "00100000")
);
begin
    --  Check each pattern.
	for n in patterns'range loop
    --  Set the inputs.
		wd <= patterns(n).wd;
		ws <= patterns(n).ws;
        rs1 <= patterns(n).rs1;
		rs2 <= patterns(n).rs2;
		clk <= patterns(n).clk;
		we <= patterns(n).we;
    --  Wait for the results.
		wait for 1 ns;
    --  Check the outputs.
		assert rd1 = patterns(n).rd1
		report "bad rd1 value" severity error;
		assert rd2 = patterns(n).rd2
		report "bad rd2 value" severity error;
	end loop;
	assert false report "end of test" severity note;
    --  Wait forever; this will finish the simulation.
	wait;
end process;
end behav;

Part1/regb_tb.vcd
$date
  Tue May  3 22:40:50 2022
$end
$version
  GHDL v0
$end
$timescale
  1 fs
$end
$scope module standard $end
$upscope $end
$scope module std_logic_1164 $end
$upscope $end
$scope module regb_tb $end
$var reg 8 ! wd[7:0] $end
$var reg 2 " ws[1:0] $end
$var reg 2 # rs1[1:0] $end
$var reg 2 $ rs2[1:0] $end
$var reg 1 % clk $end
$var reg 1 & we $end
$var reg 8 ' rd1[7:0] $end
$var reg 8 ( rd2[7:0] $end
$scope module regbank $end
$var reg 8 ) wd[7:0] $end
$var reg 2 * ws[1:0] $end
$var reg 2 + rs1[1:0] $end
$var reg 2 , rs2[1:0] $end
$var reg 1 - clk $end
$var reg 1 . we $end
$var reg 8 / rd1[7:0] $end
$var reg 8 0 rd2[7:0] $end
$var reg 4 1 w[3:0] $end
$var reg 8 2 r0[7:0] $end
$var reg 8 3 r1[7:0] $end
$var reg 8 4 r2[7:0] $end
$var reg 8 5 r3[7:0] $end
$scope module demuxws $end
$var reg 1 6 i $end
$var reg 2 7 s[1:0] $end
$var reg 4 8 y[3:0] $end
$upscope $end
$scope module reg0 $end
$var reg 8 9 i[7:0] $end
$var reg 1 : clock $end
$var reg 1 ; enable $end
$var reg 8 < o[7:0] $end
$upscope $end
$scope module reg1 $end
$var reg 8 = i[7:0] $end
$var reg 1 > clock $end
$var reg 1 ? enable $end
$var reg 8 @ o[7:0] $end
$upscope $end
$scope module reg2 $end
$var reg 8 A i[7:0] $end
$var reg 1 B clock $end
$var reg 1 C enable $end
$var reg 8 D o[7:0] $end
$upscope $end
$scope module reg3 $end
$var reg 8 E i[7:0] $end
$var reg 1 F clock $end
$var reg 1 G enable $end
$var reg 8 H o[7:0] $end
$upscope $end
$scope module muxrd1 $end
$var reg 8 I i0[7:0] $end
$var reg 8 J i1[7:0] $end
$var reg 8 K i2[7:0] $end
$var reg 8 L i3[7:0] $end
$var reg 2 M s[1:0] $end
$var reg 8 N y[7:0] $end
$upscope $end
$scope module muxrd2 $end
$var reg 8 O i0[7:0] $end
$var reg 8 P i1[7:0] $end
$var reg 8 Q i2[7:0] $end
$var reg 8 R i3[7:0] $end
$var reg 2 S s[1:0] $end
$var reg 8 T y[7:0] $end
$upscope $end
$upscope $end
$upscope $end
$enddefinitions $end
#0
b00000100 !
b00 "
b00 #
b01 $
0%
1&
b00000000 '
b00000000 (
b00000100 )
b00 *
b00 +
b01 ,
0-
1.
b00000000 /
b00000000 0
b0001 1
b00000000 2
b00000000 3
b00000000 4
b00000000 5
16
b00 7
b0001 8
b00000100 9
0:
1;
b00000000 <
b00000100 =
0>
0?
b00000000 @
b00000100 A
0B
0C
b00000000 D
b00000100 E
0F
0G
b00000000 H
b00000000 I
b00000000 J
b00000000 K
b00000000 L
b00 M
b00000000 N
b00000000 O
b00000000 P
b00000000 Q
b00000000 R
b01 S
b00000000 T
#1000000
1%
b00000100 '
1-
b00000100 /
b00000100 2
1:
b00000100 <
1>
1B
1F
b00000100 I
b00000100 N
b00000100 O
#2000000
b00000000 !
b01 "
b10 #
0%
b00000000 '
b00000000 )
b01 *
b10 +
0-
b00000000 /
b0010 1
b01 7
b0010 8
b00000000 9
0:
0;
b00000000 =
0>
1?
b00000000 A
0B
b00000000 E
0F
b10 M
b00000000 N
#3000000
b00100000 !
b00 #
1%
0&
b00000100 '
b00100000 (
b00100000 )
b00 +
1-
0.
b00000100 /
b00100000 0
b0000 1
b00100000 3
06
b0000 8
b00100000 9
1:
b00100000 =
1>
0?
b00100000 @
b00100000 A
1B
b00100000 E
1F
b00100000 J
b00 M
b00000100 N
b00100000 P
b00100000 T
#4000000
b00000100 !
b00 "
0%
b00000100 )
b00 *
0-
b00 7
b00000100 9
0:
b00000100 =
0>
b00000100 A
0B
b00000100 E
0F
#5000000
1%
1-
1:
1>
1B
1F
#6000000
b00000010 !
b11 "
b10 #
b11 $
0%
1&
b00000000 '
b00000000 (
b00000010 )
b11 *
b10 +
b11 ,
0-
1.
b00000000 /
b00000000 0
b1000 1
16
b11 7
b1000 8
b00000010 9
0:
b00000010 =
0>
b00000010 A
0B
b00000010 E
0F
1G
b10 M
b00000000 N
b11 S
b00000000 T
#7000000
b00000100 !
1%
b00000100 (
b00000100 )
1-
b00000100 0
b00000100 5
b00000100 9
1:
b00000100 =
1>
b00000100 A
1B
b00000100 E
1F
b00000100 H
b00000100 L
b00000100 R
b00000100 T
#8000000
b00001000 !
b10 "
0%
b00001000 )
b10 *
0-
b0100 1
b10 7
b0100 8
b00001000 9
0:
b00001000 =
0>
b00001000 A
0B
1C
b00001000 E
0F
0G
#9000000
b01 $
1%
b00001000 '
b00100000 (
b01 ,
1-
b00001000 /
b00100000 0
b00001000 4
1:
1>
1B
b00001000 D
1F
b00001000 K
b00001000 N
b00001000 Q
b01 S
b00100000 T
